Workbook

Sheet Sheet1
A1: Budget | B1: (All)
A3: Sum of Amount | B3: Column Labels
B4: Education | C4: Education Total | D4: Entertainment | E4: Entertainment Total | F4: Food | G4: Food Total | H4: Health | I4: Health Total | J4: Shopping | K4: Shopping Total | L4: Travel | M4: Travel Total | N4: Utilities | O4: Utilities Total | P4: (blank) | Q4: (blank) Total | R4: Grand Total
A5: Row Labels | B5: 11100 | D5: 16190 | F5: 30265 | H5: 1320 | J5: 2500 | L5: 12375 | N5: 5000 | P5: (blank)
A6: Card | B6: 1530 | C6: 1530 | D6: 8000 | E6: 8000 | J6: 1200 | K6: 1200 | P6: 18505 | Q6: 18505 | R6: 29235
A7: Cash | F7: 5000 | G7: 5000 | L7: 2000 | M7: 2000 | N7: 3025 | O7: 3025 | P7: 24460 | Q7: 24460 | R7: 34485
A8: UPI | H8: 1000 | I8: 1000 | P8: 23600 | Q8: 23600 | R8: 24600
A9: Grand Total | B9: 1530 | C9: 1530 | D9: 8000 | E9: 8000 | F9: 5000 | G9: 5000 | H9: 1000 | I9: 1000 | J9: 1200 | K9: 1200 | L9: 2000 | M9: 2000 | N9: 3025 | O9: 3025 | P9: 66565 | Q9: 66565 | R9: 88320

Sheet Expence
A1: Date | B1: Category | C1: Expense Detail | D1: Amount | E1: Payment Method | F1: Budget | G1: Category | H1: Total Expence | I1: Difference | J1: Month | K1: Day | L1: Year
A2: 45658 | B2: Food | C2: Breakfast | D2: 5000 | E2: Cash | F2: 10000 | G2: Food | H2: =SUMIF(B2:B23,"Food",D2:D23) -> 30265 | I2: =F2-H2 -> -20265 | J2: 1 | K2: 1 | L2: 2025
A3: 45659 | B3: Travel | C3: Bus fare | D3: 2000 | E3: Cash | F3: 15000 | G3: Travel | H3: =SUMIF(B2:B23,"Travel",D2:D23) -> 12375 | I3: =F3-H3 -> 2625 | J3: 1 | K3: 2 | L3: 2025
A4: 45660 | B4: Food | C4: Lunch | D4: 8000 | E4: Card | F4: 20000 | G4: Entertainment | H4: =SUMIF(B2:B23,"Entertainment",D2:D23) -> 16190 | I4: =F4-H4 -> 3810 | J4: 1 | K4: 3 | L4: 2025
A5: 45661 | B5: Entertainment | C5: Movie ticket | D5: 1200 | E5: Card | F5: 5000 | G5: Shopping | H5: =SUMIF(B2:B23,"Shopping",D2:D23) -> 2500 | I5: =F5-H5 -> 2500 | J5: 1 | K5: 4 | L5: 2025
A6: 45662 | B6: Shopping | C6: Bags | D6: 1530 | E6: Card | F6: 5000 | G6: Education | H6: =SUMIF(B2:B23,"Education",D2:D23) -> 11100 | I6: =F6-H6 -> -6100 | J6: 1 | K6: 5 | L6: 2025
A7: 45663 | B7: Food | C7: Snacks | D7: 3025 | E7: Cash | F7: 2000 | G7: Utilities | H7: =SUMIF(B2:B23,"Utilities",D2:D23) -> 5000 | I7: =F7-H7 -> -3000 | J7: 1 | K7: 6 | L7: 2025
A8: 45664 | B8: Travel | C8: Taxi | D8: 1000 | E8: UPI | F8: 2000 | G8: Health | H8: =SUMIF(B2:B23,"Health",D2:D23) -> 1320 | I8: =F8-H8 -> 680 | J8: 1 | K8: 7 | L8: 2025
A9: 45665 | B9: Education | C9: Notebook | D9: 4500 | E9: Cash | J9: 1 | K9: 8 | L9: 2025
A10: 45666 | B10: Utilities | C10: Mobile recharge | D10: 2000 | E10: UPI | J10: 1 | K10: 9 | L10: 2025
A11: 45667 | B11: Food | C11: Dinner | D11: 1140 | E11: Card | J11: 1 | K11: 10 | L11: 2025
A12: 45668 | B12: Shopping | C12: Footwear | D12: 6800 | E12: Cash | J12: 1 | K12: 11 | L12: 2025
A13: 45669 | B13: Entertainment | C13: Online subscription | D13: 9990 | E13: Card | J13: 1 | K13: 12 | L13: 2025
A14: 45670 | B14: Travel | C14: Train ticket | D14: 7500 | E14: UPI | J14: 1 | K14: 13 | L14: 2025
A15: 45671 | B15: Health | C15: Medicine | D15: 1320 | E15: Cash | J15: 1 | K15: 14 | L15: 2025
A16: 45672 | B16: Food | C16: Coffee | D16: 4000 | E16: Cash | J16: 1 | K16: 15 | L16: 2025
A17: 45673 | B17: Shopping | C17: Clothes | D17: 2500 | E17: Card | J17: 1 | K17: 16 | L17: 2025
A18: 45674 | B18: Education | C18: Stationery | D18: 6600 | E18: Cash | J18: 1 | K18: 17 | L18: 2025
A19: 45675 | B19: Food | C19: Lunch | D19: 9100 | E19: UPI | J19: 1 | K19: 18 | L19: 2025
A20: 45676 | B20: Travel | C20: Fuel | D20: 1875 | E20: Card | J20: 1 | K20: 19 | L20: 2025
... A23: 45679 | B23: Utilities | C23: Internet bill | D23: 3000 | E23: Card | J23: 1 | K23: 22 | L23: 2025

Sheet Budget
A1: Difference
A2: =Expence!F2-Expence!H2 -> -20265
A3: =Expence!F3-Expence!H3 -> 2625
A4: =Expence!F4-Expence!H4 -> 3810
A5: =Expence!F5-Expence!H5 -> 2500
A6: =Expence!F6-Expence!H6 -> -6100
A7: =Expence!F7-Expence!H7 -> -3000
A8: =Expence!F8-Expence!H8 -> 680

Sheet Chart
